<?xml version="1.0"?>
<!--<!DOCTYPE metadata SYSTEM "http://www.esri.com/metadata/esriprof80.dtd">-->
<metadata xml:lang="fr"><Esri><CreaDate>20100902</CreaDate><CreaTime>11221200</CreaTime><SyncOnce>TRUE</SyncOnce><MetaID>{D0C24B74-9988-442E-A48E-A567CCB5940F}</MetaID></Esri><idinfo><citation><citeinfo><onlink Sync="TRUE">\\CCER51\C$\ACTIV2010\BNGRC\REG_SAVA\DIST_SAMBAVA\lim_fkt_com_morafeno</onlink></citeinfo></citation></idinfo><distInfo><distributor><distorTran><onLineSrc><linkage Sync="TRUE">file://\\CCER51\C$\ACTIV2010\BNGRC\REG_SAVA\DIST_SAMBAVA\lim_fkt_com_morafeno</linkage><protocol Sync="TRUE">Local Area Network</protocol></onLineSrc></distorTran></distributor></distInfo><dataqual><lineage><procstep><procdesc Sync="TRUE">Dataset copied.</procdesc><srcused Sync="TRUE">C:\ACTIV2010\BNGRC\MERGE_SAVA\lim_fkt_com_morafeno</srcused><date Sync="TRUE">20100902</date><time Sync="TRUE">11221200</time></procstep></lineage></dataqual></metadata>
